LICENSE
README.md
setup.cfg
setup.py
nlsql_api/__init__.py
nlsql_api/choices.py
nlsql_api/client.py
nlsql_api/models.py
nlsql_api.egg-info/PKG-INFO
nlsql_api.egg-info/SOURCES.txt
nlsql_api.egg-info/dependency_links.txt
nlsql_api.egg-info/requires.txt
nlsql_api.egg-info/top_level.txt