Metadata-Version: 2.1
Name: nlsql-api
Version: 0.0.5
Summary: Python client for NLSQL API
Home-page: https://github.com/denissa4/nlsql-api
License: UNKNOWN
Project-URL: Source Code, https://github.com/denissa4/nlsql-api
Project-URL: Issue Tracker, https://github.com/denissa4/nlsql-api/issues
Platform: UNKNOWN
Requires-Python: >=3.7, <4
License-File: LICENSE
